AChaM.v
module odd_upordown_counter(
   input Clk,
    input reset,      // active high reset
    input UpOrDown,   // high for UP counter and low for Down counter
    output reg [3:0] Count
);
    // Internal states for odd numbers only
    reg [3:0] odd_count [7:0]; // Store the 8 odd states (0001, 0011, 0101, ..., 1111)
    integer i;

    // Initialize the odd_count array with the odd states
    initial begin
        odd_count[0] = 4'b0001;
        odd_count[1] = 4'b0011;
        odd_count[2] = 4'b0101;
        odd_count[3] = 4'b0111;
        odd_count[4] = 4'b1001;
        odd_count[5] = 4'b1011;
        odd_count[6] = 4'b1101;
        odd_count[7] = 4'b1111;
    end

    // Counter behavior based on the clock and reset
    always @(posedge Clk or posedge reset) begin
        if (reset) 
            Count <= 4'b0001;  // Reset the counter to 0001
        else if (UpOrDown)    // Up mode selected
            begin
                // Find current state index and increment
                for (i = 0; i < 7; i = i + 1) begin
                    if (Count == odd_count[i]) begin
                        Count <= odd_count[i + 1];
                    end
                end
                // Wrap around to first odd number if the count is 1111
                if (Count == 4'b1111)
                    Count <= 4'b0001;
            end
        else                  // Down mode selected
            begin
                // Find current state index and decrement
                for (i = 1; i < 8; i = i + 1) begin
                    if (Count == odd_count[i]) begin
                        Count <= odd_count[i - 1];
                    end
                end
                // Wrap around to 1111 if the count is 0001
                if (Count == 4'b0001)
                    Count <= 4'b1111;
            end
    end

endmodule

AChaM_tb.v
// Max Benedict Chavez, S16
module odd_upordown_counter_tb;

    reg clk, reset, UpOrDown;
    wire [3:0] Count;
    
    // Instantiate the counter
    odd_upordown_counter uut (
        .Clk(clk),
        .reset(reset),
        .UpOrDown(UpOrDown),
        .Count(Count)
    );
    
    // Clock generation
    always begin
        #5 clk = ~clk; // Clock with 10 time unit period
    end
    
    // Test stimulus
    initial begin
        // Initialize signals
        clk = 0;
        reset = 0;
        UpOrDown = 1;  // Start with Up mode
        
        // Reset counter
        #10 reset = 1;
        #10 reset = 0;
        
        // Count Up (odd numbers from 0001 to 1111)
        #100 UpOrDown = 1;  // Up mode
        
        // Count Down (odd numbers from 1111 to 0001)
        #100 UpOrDown = 0;  // Down mode
        
        // Finish the simulation
        #50 $finish;
    end
    
    // Monitor the counter value
    initial begin
      $display("Written by Max Benedict Chavez using Behavioral Modelling");
      $display("Odd Up Down Binary Counter");
      $monitor("Time=%0t, Reset=%b, UpOrDown=%b, Count=%b", $time, reset, UpOrDown, Count);
      $dumpfile("AGTKChaM.vcd"); //gtkwave
      $dumpvars();
    end
    
endmodule

AGTKChaM.vcd
$date
	Sun Apr  6 02:04:36 2025
$end
$version
	Icarus Verilog
$end
$timescale
	1s
$end
$scope module odd_upordown_counter_tb $end
$var wire 4 ! Count [3:0] $end
$var reg 1 " UpOrDown $end
$var reg 1 # clk $end
$var reg 1 $ reset $end
$scope module uut $end
$var wire 1 # Clk $end
$var wire 1 " UpOrDown $end
$var wire 1 $ reset $end
$var reg 4 % Count [3:0] $end
$var integer 32 & i [31:0] $end
$upscope $end
$upscope $end
$enddefinitions $end
$comment Show the parameter values. $end
$dumpall
$end
#0
$dumpvars
bx &
bx %
0$
0#
1"
bx !
$end
#5
b111 &
1#
#10
b1 !
b1 %
0#
1$
#15
1#
#20
0#
0$
#25
b11 !
b11 %
b111 &
1#
#30
0#
#35
b101 !
b101 %
b111 &
1#
#40
0#
#45
b111 !
b111 %
b111 &
1#
#50
0#
#55
b1001 !
b1001 %
b111 &
1#
#60
0#
#65
b1011 !
b1011 %
b111 &
1#
#70
0#
#75
b1101 !
b1101 %
b111 &
1#
#80
0#
#85
b1111 !
b1111 %
b111 &
1#
#90
0#
#95
b1 !
b1 %
b111 &
1#
#100
0#
#105
b11 !
b11 %
b111 &
1#
#110
0#
#115
b101 !
b101 %
b111 &
1#
#120
0#
#125
b111 !
b111 %
b111 &
1#
#130
0#
#135
b1001 !
b1001 %
b111 &
1#
#140
0#
#145
b1011 !
b1011 %
b111 &
1#
#150
0#
#155
b1101 !
b1101 %
b111 &
1#
#160
0#
#165
b1111 !
b1111 %
b111 &
1#
#170
0#
#175
b1 !
b1 %
b111 &
1#
#180
0#
#185
b11 !
b11 %
b111 &
1#
#190
0#
#195
b101 !
b101 %
b111 &
1#
#200
0#
#205
b111 !
b111 %
b111 &
1#
#210
0#
#215
b1001 !
b1001 %
b111 &
1#
#220
0#
0"
#225
b111 !
b111 %
b1000 &
1#
#230
0#
#235
b101 !
b101 %
b1000 &
1#
#240
0#
#245
b11 !
b11 %
b1000 &
1#
#250
0#
#255
b1 !
b1 %
b1000 &
1#
#260
0#
#265
b1111 !
b1111 %
b1000 &
1#
